MANIFEST.in
README.rst
setup.py
test_algorithm/__init__.py
test_algorithm/configs.py
test_algorithm/random_number.py
test_algorithm/vsource_configs.py
test_algorithm/vsource_service.py
vsource/__init__.py
vsource/configs.py
vsource/loginInstance.py
vsource.egg-info/PKG-INFO
vsource.egg-info/SOURCES.txt
vsource.egg-info/dependency_links.txt
vsource.egg-info/requires.txt
vsource.egg-info/top_level.txt
vsource/algorithms/__init__.py
vsource/algorithms/anime_gan_v2.py
vsource/algorithms/binary_segmentation.py
vsource/algorithms/cod_cpd.py
vsource/algorithms/face_attribute.py
vsource/algorithms/face_attribute_x.py
vsource/algorithms/face_detection.py
vsource/algorithms/face_generation.py
vsource/algorithms/face_recognition.py
vsource/algorithms/github_avatar_generation.py
vsource/algorithms/hrnet_landmark_detection.py
vsource/algorithms/landmark_detection.py
vsource/algorithms/maze_generation.py
vsource/algorithms/new_algorithm.py
vsource/algorithms/random_number.py
vsource/algorithms/remove_bg.py
vsource/algorithms/salient_object_detection.py
vsource/algorithms/speaker_recognition.py
vsource/algorithms/text_generation.py
vsource/exceptions/__init__.py
vsource/scripts/__init__.py
vsource/scripts/algorithm_scripts/__init__.py
vsource/scripts/algorithm_scripts/algorithm-configs.template
vsource/scripts/algorithm_scripts/algorithm-deploy-compose.template
vsource/scripts/algorithm_scripts/algorithm-dockerfile.template
vsource/scripts/algorithm_scripts/algorithm-local-start.template
vsource/scripts/algorithm_scripts/algorithm-logs.template
vsource/scripts/algorithm_scripts/algorithm-service.template
vsource/scripts/algorithm_scripts/algorithm-start.template
vsource/scripts/algorithm_scripts/algorithm-stop.template
vsource/scripts/algorithm_scripts/algorithms.py
vsource/scripts/enroll_service/__init__.py
vsource/scripts/enroll_service/deployment.yaml.template